rSTSF/__init__.py
rSTSF/rstsf.py
rSTSF-0.1.1.dist-info/LICENSE
rSTSF-0.1.1.dist-info/METADATA
rSTSF-0.1.1.dist-info/WHEEL
rSTSF-0.1.1.dist-info/top_level.txt
rSTSF-0.1.1.dist-info/RECORD
