Metadata-Version: 2.1
Name: rSTSF
Version: 0.1.1
Summary: Fast, accurate and explainable time series classification through randomization
Home-page: https://github.com/stevcabello/r-STSF
Author: Nestor Cabello
Author-email: stevcabello@gmail.com
Classifier: Programming Language :: Python :: 3
Classifier: License :: OSI Approved :: MIT License
Classifier: Operating System :: OS Independent
Requires-Python: >=3.6
License-File: LICENSE
Requires-Dist: numpy
Requires-Dist: pandas
Requires-Dist: scikit-learn
Requires-Dist: scipy
Requires-Dist: numba
Requires-Dist: pyfftw
Requires-Dist: matplotlib
Requires-Dist: statsmodels
